gwh/__init__.py
gwh/__main__.py
gwh/__version__.py
gwh/gitlab_api.py
gwh/helpers.py
gwh-1.0.2.dist-info/LICENSE
gwh-1.0.2.dist-info/METADATA
gwh-1.0.2.dist-info/WHEEL
gwh-1.0.2.dist-info/top_level.txt
gwh-1.0.2.dist-info/RECORD
