Metadata-Version: 2.1
Name: gwh
Version: 1.0.2
Summary: Webhook Handler for GitLab
Home-page: https://github.com/ahebrank/gitlab-webhook-handler
Author: Andy Hebrank
Author-email: ahebrank@gmail.com
License: Apache License, Version 2.0
Platform: UNKNOWN
License-File: LICENSE
Requires-Dist: Flask (>=1.0)
Requires-Dist: requests (>=2.19.0)
